sqlite_ast_conformance/__init__.py
sqlite_ast_conformance/ast-tests/clause_all.json
sqlite_ast_conformance/ast-tests/clause_distinct.json
sqlite_ast_conformance/ast-tests/clause_group_by.json
sqlite_ast_conformance/ast-tests/clause_having.json
sqlite_ast_conformance/ast-tests/clause_limit.json
sqlite_ast_conformance/ast-tests/clause_limit_offset.json
sqlite_ast_conformance/ast-tests/clause_order_by.json
sqlite_ast_conformance/ast-tests/clause_order_by_nulls.json
sqlite_ast_conformance/ast-tests/clause_where.json
sqlite_ast_conformance/ast-tests/clause_where_complex.json
sqlite_ast_conformance/ast-tests/compound_except.json
sqlite_ast_conformance/ast-tests/compound_intersect.json
sqlite_ast_conformance/ast-tests/compound_triple.json
sqlite_ast_conformance/ast-tests/compound_union.json
sqlite_ast_conformance/ast-tests/compound_union_all.json
sqlite_ast_conformance/ast-tests/compound_with_order.json
sqlite_ast_conformance/ast-tests/correlated_subquery.json
sqlite_ast_conformance/ast-tests/expr_arithmetic.json
sqlite_ast_conformance/ast-tests/expr_between.json
sqlite_ast_conformance/ast-tests/expr_bitwise.json
sqlite_ast_conformance/ast-tests/expr_case_searched.json
sqlite_ast_conformance/ast-tests/expr_case_simple.json
sqlite_ast_conformance/ast-tests/expr_cast.json
sqlite_ast_conformance/ast-tests/expr_collate.json
sqlite_ast_conformance/ast-tests/expr_comparison.json
sqlite_ast_conformance/ast-tests/expr_exists.json
sqlite_ast_conformance/ast-tests/expr_glob.json
sqlite_ast_conformance/ast-tests/expr_in_list.json
sqlite_ast_conformance/ast-tests/expr_in_subquery.json
sqlite_ast_conformance/ast-tests/expr_is_not_false.json
sqlite_ast_conformance/ast-tests/expr_is_not_null.json
sqlite_ast_conformance/ast-tests/expr_is_null.json
sqlite_ast_conformance/ast-tests/expr_is_true.json
sqlite_ast_conformance/ast-tests/expr_like.json
sqlite_ast_conformance/ast-tests/expr_logical.json
sqlite_ast_conformance/ast-tests/expr_string_concat.json
sqlite_ast_conformance-0.1.dist-info/METADATA
sqlite_ast_conformance-0.1.dist-info/WHEEL
sqlite_ast_conformance-0.1.dist-info/top_level.txt
sqlite_ast_conformance-0.1.dist-info/RECORD
