Metadata-Version: 2.4
Name: sqlite-ast-conformance
Version: 0.1
Summary: Conformance test suite for SQLite SQL parsers, using JSON AST fixtures from the official SQLite parser
Project-URL: Homepage, https://github.com/simonw/sqlite-ast-conformance
Requires-Python: >=3.10
